instancespace/__init__.py
instancespace/_serialisers.py
instancespace/data/__init__.py
instancespace/data/default_options.py
instancespace/data/metadata.py
instancespace/data/model.py
instancespace/data/options.py
instancespace/example.ipynb
instancespace/instance_space.py
instancespace/model.py
instancespace/scripting/__init__.py
instancespace/scripting/script_disc.py
instancespace/scripting/script_fcn.py
instancespace/stage_builder.py
instancespace/stage_runner.py
instancespace/stages/__init__.py
instancespace/stages/cloister.py
instancespace/stages/pilot.py
instancespace/stages/prelim.py
instancespace/stages/preprocessing.py
instancespace/stages/pythia.py
instancespace/stages/sifted.py
instancespace/stages/stage.py
instancespace/stages/trace.py
instancespace/utils/__init__.py
instancespace/utils/filter.py
instancespace-0.2.1.dist-info/LICENSE
instancespace-0.2.1.dist-info/METADATA
instancespace-0.2.1.dist-info/WHEEL
instancespace-0.2.1.dist-info/RECORD
