Metadata-Version: 2.1
Name: instancespace
Version: 0.2.1
Summary: 
Author: Kushagra Khare
Author-email: kharek@student.unimelb.edu.au
Requires-Python: >=3.12,<4.0
Classifier: Programming Language :: Python :: 3
Classifier: Programming Language :: Python :: 3.12
Classifier: Programming Language :: Python :: 3.13
Requires-Dist: alphashape (>=1.3.1,<2.0.0)
Requires-Dist: black (>=24.4.2,<25.0.0)
Requires-Dist: click (>=8.1.7,<9.0.0)
Requires-Dist: loguru (>=0.7.2,<0.8.0)
Requires-Dist: matplotlib (>=3.9.2,<4.0.0)
Requires-Dist: numpy (>=1.26.4,<2.0.0)
Requires-Dist: pandas (>=2.2.1,<3.0.0)
Requires-Dist: pandas-stubs (>=2.2.1.240316,<3.0.0.0)
Requires-Dist: pygad (>=3.3.1,<4.0.0)
Requires-Dist: scikit-learn (>=1.5.2,<2.0.0)
Requires-Dist: scikit-optimize (>=0.10.2,<0.11.0)
Requires-Dist: scipy (>=1.13.0,<2.0.0)
Requires-Dist: shapely (>=2.0.5,<3.0.0)
